app/__init__.py
app/cli.py
app/decorators.py
tips_tricks-0.1.2.dist-info/METADATA
tips_tricks-0.1.2.dist-info/WHEEL
tips_tricks-0.1.2.dist-info/entry_points.txt
tips_tricks-0.1.2.dist-info/top_level.txt
tips_tricks-0.1.2.dist-info/RECORD
