Metadata-Version: 2.4
Name: tips-tricks
Version: 0.1.2
Summary: CLI tool for processing text files and counting characters
Author: Katsiaryna Shymko
Classifier: Programming Language :: Python :: 3
Classifier: Operating System :: OS Independent
Requires-Python: >=3.7
Dynamic: author
Dynamic: classifier
Dynamic: requires-python
Dynamic: summary
